occultist/__init__.py
occultist-0.1.0.dist-info/WHEEL
occultist-0.1.0.dist-info/METADATA
occultist-0.1.0.dist-info/RECORD
