Metadata-Version: 2.1
Name: occultist
Version: 0.1.0
Summary: Implementation of Cypher for Python
License: MIT
Author: askerka
Requires-Python: >=3.8,<4.0
Classifier: License :: OSI Approved :: MIT License
Classifier: Programming Language :: Python :: 3
Classifier: Programming Language :: Python :: 3.8
Classifier: Programming Language :: Python :: 3.9
